Workbook

Sheet 前提条件
A1: VERION 事業計画詳細 v2.0 ── 前提条件（Assumptions）
A2: 青字=入力（計画値）。すべて目標・計画・試算であり確約ではありません。2026-07 現行計画（調達ラダー v5.0 系）に整合。
A4: 項目 | B4: 単位 | C4: 2027 | D4: 2028 | E4: 2029 | F4: 2030 | G4: 2031 | H4: 2032 | I4: 備考
A5: MAU | B5: 万人 | C5: 10 | D5: 25 | E5: 50 | F5: 80 | G5: 150 | H5: 300 | I5: 2027=A条件 MAU10万 / 2028=B条件 25万 / 2029=C条件 50万。以降は計画。北極星は10年でMAU1億
A6: 課金率 | B6: % | C6: 0.02 | D6: 0.04 | E6: 0.06 | F6: 0.08 | G6: 0.1 | H6: 0.1 | I6: 計画レンジ 2%→6%→10%（カード経済圏の完成に伴い上昇）
A7: 課金ユーザー | B7: 万人 | C7: =C5*C6 | D7: =D5*D6 | E7: =E5*E6 | F7: =F5*F6 | G7: =G5*G6 | H7: =H5*H6 | I7: =MAU×課金率
A8: カード単価 | B8: 円 | C8: 3000 | D8: 3000 | E8: 3000 | F8: 3000 | G8: 3000 | H8: 3000 | I8: 約20USD/枚（ガチャ1回・9分割ピース1枚）
A9: 月間購入枚数 | B9: 枚/人 | C9: 2 | D9: 2.2 | E9: 2.4 | F9: 2.6 | G9: 2.8 | H9: 2.8 | I9: 課金ユーザー1人あたり。サイト試算の2.8枚に漸近
A10: スポンサー社数 | B10: 社 | C10: 0 | D10: 10 | E10: 20 | F10: 40 | G10: 70 | H10: 100 | I10: 広告クイズ・大会協賛。賞金原資は別建て（P&L外）
A11: スポンサー平均単価 | B11: 万円/年 | C11: 1500 | D11: 1500 | E11: 1500 | F11: 1500 | G11: 1500 | H11: 1500 | I11: 約10万USD/年・社
A12: 広告・データARPU | B12: 円/MAU/年 | C12: 0 | D12: 200 | E12: 600 | F12: 1200 | G12: 2000 | H12: 2600 | I12: リワード広告+IPデータライセンス+ターゲティング（Phase3で主役化）
A13: SC決済関連収益 | B13: 億円 | C13: 0 | D13: 0 | E13: 0 | F13: 0 | G13: 5 | H13: 15 | I13: 上場後構想（フロート・決済マージン等）。金融免許取得を前提とする構想値
A14: USD/JPY | B14: 円 | C14: 160 | D14: 160 | E14: 160 | F14: 160 | G14: 160 | H14: 160 | I14: 換算レート（前提）
A16: ※ 賞金はスポンサー協賛金のみを原資とし、本P&Lの収益にも費用にも含めない（入口/出口分離の設計）。

Sheet 売上計画
A1: 売上計画（Revenue Build-up）
A2: 緑字=前提条件シート参照。単位: 億円。3.6 = 10,000人×3,000円×12ヶ月÷1億（万人→億円換算係数）
A4: 項目 | B4: 単位 | C4: 2027 | D4: 2028 | E4: 2029 | F4: 2030 | G4: 2031 | H4: 2032 | I4: 備考
A5: カード売上（ガチャ） | B5: 億円 | C5: =前提条件!C5*前提条件!C6*前提条件!C9*3.6 | D5: =前提条件!D5*前提条件!D6*前提条件!D9*3.6 | E5: =前提条件!E5*前提条件!E6*前提条件!E9*3.6 | F5: =前提条件!F5*前提条件!F6*前提条件!F9*3.6 | G5: =前提条件!G5*前提条件!G6*前提条件!G9*3.6 | H5: =前提条件!H5*前提条件!H6*前提条件!H9*3.6 | I5: =MAU×課金率×枚数×3,000円×12。売上の背骨（Phase1）
A6: スポンサー収入 | B6: 億円 | C6: =前提条件!C10*前提条件!C11/10000 | D6: =前提条件!D10*前提条件!D11/10000 | E6: =前提条件!E10*前提条件!E11/10000 | F6: =前提条件!F10*前提条件!F11/10000 | G6: =前提条件!G10*前提条件!G11/10000 | H6: =前提条件!H10*前提条件!H11/10000 | I6: =社数×平均単価（Phase2）
A7: 広告・データ収益 | B7: 億円 | C7: =前提条件!C5*前提条件!C12/10000 | D7: =前提条件!D5*前提条件!D12/10000 | E7: =前提条件!E5*前提条件!E12/10000 | F7: =前提条件!F5*前提条件!F12/10000 | G7: =前提条件!G5*前提条件!G12/10000 | H7: =前提条件!H5*前提条件!H12/10000 | I7: =MAU×広告データARPU（Phase2→3）
A8: SC決済関連（構想） | B8: 億円 | C8: =前提条件!C13 | D8: =前提条件!D13 | E8: =前提条件!E13 | F8: =前提条件!F13 | G8: =前提条件!G13 | H8: =前提条件!H13 | I8: 上場後・金融免許取得後の構想値（Phase4）
A9: 年商合計 | B9: 億円 | C9: =SUM(C5:C8) | D9: =SUM(D5:D8) | E9: =SUM(E5:E8) | F9: =SUM(F5:F8) | G9: =SUM(G5:G8) | H9: =SUM(H5:H8)
A11: 整合メモ: 2031（IPO年）の年商は約200億円 ── サイト記載「IPO時 時価総額1,000億シナリオ＝年商100〜200億の水準」と整合。
A12: 整合メモ: 北極星（時価総額1兆円）の前提年商1,000〜2,000億は、課金100〜200万人（MAU 1,000万〜2,000万×10%）で到達する将来目盛。

Sheet コストとPL
A1: コスト構造と年次P&L
A2: 青字=入力（計画値）。単位: 億円。少数精鋭×AI内製が費用構造の前提。賞金はスポンサー原資のため費用に含まない。
A4: 項目 | B4: 単位 | C4: 2027 | D4: 2028 | E4: 2029 | F4: 2030 | G4: 2031 | H4: 2032 | I4: 備考
A5: 人員数 | B5: 人 | C5: 12 | D5: 18 | E5: 25 | F5: 35 | G5: 50 | H5: 70 | I5: 少数精鋭 ── 制作・運営・多言語化をAIが担う
A6: 人件費 | B6: 億円 | C6: =C5*0.12 | D6: =D5*0.12 | E6: =E5*0.12 | F6: =F5*0.12 | G6: =G5*0.12 | H6: =H5*0.12 | I6: =人員×平均年収1,200万円（0.12億）
A7: サーバー・インフラ | B7: 億円 | C7: 0.5 | D7: 0.9 | E7: 1.5 | F7: 2.5 | G7: 4.5 | H7: 8
A8: GPU・独自AI投資 | B8: 億円 | C8: 0.8 | D8: 1.5 | E8: 2 | F8: 2.5 | G8: 3 | H8: 4 | I8: 数千万〜億円単位（owner方針）。クイズ生成・演出DB・アニメ生成の生産設備
A9: IPロイヤリティ | B9: 億円 | C9: =売上計画!C5*0.08 | D9: =売上計画!D5*0.08 | E9: =売上計画!E5*0.08 | F9: =売上計画!F5*0.08 | G9: =売上計画!G5*0.08 | H9: =売上計画!H5*0.08 | I9: =カード売上×8%（独占ライセンスの前払い一括は資産計上・別掲）
A10: マーケティング・UA | B10: 億円 | C10: 1 | D10: 2 | E10: 6 | F10: 12 | G10: 30 | H10: 60 | I10: 景品マーケが主・広告費は従（現物資産が集客する設計）
A11: 法務・監査 | B11: 億円 | C11: 0.5 | D11: 0.7 | E11: 0.9 | F11: 1.2 | G11: 1.5 | H11: 2 | I11: 意見書4本・2027監査法人選任・上場準備
A12: オフィス・管理 | B12: 億円 | C12: 0.3 | D12: 0.5 | E12: 0.8 | F12: 1.2 | G12: 1.8 | H12: 2.5
A13: 費用合計 | B13: 億円 | C13: =SUM(C6:C12) | D13: =SUM(D6:D12) | E13: =SUM(E6:E12) | F13: =SUM(F6:F12) | G13: =SUM(G6:G12) | H13: =SUM(H6:H12)
A14: 営業損益 | B14: 億円 | C14: =売上計画!C9-C13 | D14: =売上計画!D9-D13 | E14: =売上計画!E9-E13 | F14: =売上計画!F9-F13 | G14: =売上計画!G9-G13 | H14: =売上計画!H9-H13 | I14: 2028年中の単年黒字化（シリーズB実行条件）と整合
A15: 営業利益率 | B15: % | C15: =IF(売上計画!C9=0,0,C14/売上計画!C9) | D15: =IF(売上計画!D9=0,0,D14/売上計画!D9) | E15: =IF(売上計画!E9=0,0,E14/売上計画!E9) | F15: =IF(売上計画!F9=0,0,F14/売上計画!F9) | G15: =IF(売上計画!G9=0,0,G14/売上計画!G9) | H15: =IF(売上計画!H9=0,0,H14/売上計画!H9)
A17: ※ 2027は営業赤字（シード5億+シリーズA20億が先行投資を支える）。2028に黒字転換 ── Bゲート「単年黒字化(2028年中)」の裏付け。

Sheet セル画資産
A1: セル画・原画 資産計画（新設セクション）
A2: 旧版に無い現物資産の計画。取得資金は匿名組合スキームで本体調達と分離（資金の分離）。B/S計上は取得原価・鑑定評価は参考併記。
A4: 時点 | B4: 保有枚数 | C4: 取得原価(億円) | D4: 鑑定評価(億円) | E4: 位置づけ
A5: 2026-07 現在 | B5: 1454 | C5: 6 | D5: 6 | E5: 実在の証明済み（全点鑑定書付き・まんだらけ等の真贋認定）
A6: 2027（シード期末） | B6: 4000 | D6: 12 | E6: シード期計画 ── 景品運用の開始
A7: 2028（シリーズB条件） | B7: 20000 | D7: 50 | E7: Bゲート「セル画連結 約50億円（監査済み評価）」に対応
A8: 2029（買付完了） | E8: 独占買付の完了 ── 市場在庫を「買えないもの」に
A9: 到達計画 | B9: 200000 | E9: 20万枚 ── 達成すれば世界一の保有企業（計画）
A11: 収益化6本: 展示イベント/投資家招待/関係者限定販売/レンタル/PF景品/カストディフィー ── 原則「買う。止める。売らない（売るのは所有権=NFT構想）」
A12: 保管: 寺田倉庫と協業検討中（保税・温湿度管理・24h監視・スラブ封入）。鑑定評価12億(2027)は取得ペースからの試算値。

Sheet AI・GPU投資
A1: AI・GPU 投資計画（新設セクション）
A2: 旧版に無いAI戦略。人を増やす代わりに計算資源へ投資 ── 少数精鋭経営の裏付け。金額はコストとPLシートのGPU行に整合。
A4: 項目 | B4: 単位 | C4: 2027 | D4: 2028 | E4: 2029 | F4: 2030 | G4: 2031 | H4: 2032 | I4: 備考
A5: GPU・独自AI投資 | B5: 億円 | C5: =コストとPL!C8 | D5: =コストとPL!D8 | E5: =コストとPL!E8 | F5: =コストとPL!F8 | G5: =コストとPL!G8 | H5: =コストとPL!H8 | I5: 数千万〜億円単位（owner方針）
A6: 人員数（参考） | B6: 人 | C6: =コストとPL!C5 | D6: =コストとPL!D5 | E6: =コストとPL!E5 | F6: =コストとPL!F5 | G6: =コストとPL!G5 | H6: =コストとPL!H5 | I6: AIが制作・運営を担うため低水準を維持
A7: 1人あたり年商 | B7: 億円/人 | C7: =IF(C6=0,0,売上計画!C9/C6) | D7: =IF(D6=0,0,売上計画!D9/D6) | E7: =IF(E6=0,0,売上計画!E9/E6) | F7: =IF(F6=0,0,売上計画!F9/F6) | G7: =IF(G6=0,0,売上計画!G9/G6) | H7: =IF(H6=0,0,売上計画!H9/H6) | I7: 少数精鋭×AI内製の効率指標（2032≈5.9億円/人）
A9: 投資の狙い① 自由な独自AI ── 外部APIの制約・料金・検閲に縛られないモデルを保有（基盤モデルの進歩で資金投下により到達可能と認識）
A10: 投資の狙い② クイズ自動生成 ── 全IP・全話数・多言語を24時間供給（コンテンツ原価の構造的低減）
A11: 投資の狙い③ 演出の人気DB ── ユーザーの遊びから「どのシーン・どの演出がウケるか」を蓄積。遊び場の運営者だけが持てる独占データ
A12: 投資の狙い④ AIアニメ生成 ── 常に生まれ続けるインディーズ・旧作漫画（日本企業が獲得に構造優位）を、DBを参照して理論的にアニメ化

Sheet 調達と資金使途
A1: 調達ラダーと Use of Funds
A2: 現行計画（転換型シード・ゲート連動）。旧版の「シード30億・総調達2億USD」は旧設計のため全面改訂。
A4: ラウンド | B4: 時期 | C4: 調達額(億円) | D4: 条件 | E4: 主な使途 | F4: 実行条件（ゲート）
A5: シード | B5: 2026 H2 | C5: 5 | D5: 転換型新株予約権（キャップ100億・割引20%） | E5: 開発2.0/IP独占1.5/ギャラリー・マーケ0.7/法務・監査0.5/予備0.3 | F5: 無条件払込（現物購入には充てない）
A6: シリーズA | B6: 〜2027/6 | C6: 20 | D6: 優先株1x非参加・pre200億目標 | E6: セル画10億＋IP獲得10億 | F6: PFβ・MAU10万・IP累計5件・監査法人選任・法律意見書
A7: シリーズB | B7: 〜2028/12 | C7: 35 | D7: pre350億目標 | E7: 独占買付の完了・IP契約10億 | F7: 正式ローンチ・MAU25万・単年黒字化(2028年中)・セル画連結約50億(監査済み評価)
A8: シリーズC | B8: 2029 | C8: 60 | D8: pre600億目標・テンダー併設 | E8: 目玉景品の投下・広告・賞金 | F8: MAU50万・営業黒字の継続・主幹事選定
A9: IPO | B9: 2031目標 | D9: 東証グロース想定 | E9: ── | F9: 2029 N-2期入り → 2031上場申請。IPOはスタート（金融免許→予測市場に「お金」）
A11: 資本政策: 名目ラウンド合計120億円（A=20億ケース）・放出約35%＋SOプール10%（シード前設定）＝完全希薄化後も既存・代表 約55%を維持。
A12: 規律: 各ラウンドは前段ゲートを満たしたときのみ実行。未達なら延伸し希薄化を追加しない。使い道の方針: 人件費でなく IP・GPU・現物という資産に集中投下。

Sheet 感応度とBEP
A1: 感応度分析（Base / Bear / Worst）と損益分岐点
A2: 旧版の感応度構成を踏襲。下方でも資産（承継可能IP・セル画現物・GPU）が残る設計。
A4: シナリオ | B4: MAU達成率 | C4: 課金率 | D4: 黒字化 | E4: IPO | F4: 下方の資産価値 | G4: 備考
A5: Base | B5: 1 | C5: 0.1 | D5: 2028年中 | E5: 2031 | F5: ── | G5: 計画どおり（本書の基準ケース）
A6: Bear | B6: 0.5 | C6: 0.08 | D6: 2030年 | E6: 延伸 | F6: 承継可能IP群＋セル画現物 | G6: ゲート未達→調達・上場を延伸（希薄化を追加しない）
A7: Worst | B7: 0.3 | C7: 0.05 | D7: 未達 | E7: ── | F7: IPライセンス譲渡価値＋現物＋GPU | G7: 最悪でも資産が残る守りの設計
A9: 損益分岐点（2028年コスト基準）
A10: 2028 費用合計 | B10: 億円 | C10: =コストとPL!D13
A11: BEP月商 | B11: 億円/月 | C11: =C10/12
A12: BEP課金ユーザー | B12: 万人 | C12: =C11/(前提条件!D9*0.3) | D12: =BEP月商÷(枚数×3,000円)。0.3=3,000円×10,000人÷1億。約1.1万人の課金で単月黒字圏
A14: 免責: 本書のすべての数値・時期は目標・計画・試算であり、確約ではありません。実行は調達ゲートの達成状況に連動します。
